qsar/__init__.py
qsar/gan/__init__.py
qsar/gan/extract_descriptors.py
qsar/gan/gan_featurizer.py
qsar/gan/qsar_gan.py
qsar/models/__init__.py
qsar/models/baseline_model.py
qsar/models/catboost.py
qsar/models/elasticnet.py
qsar/models/lasso.py
qsar/models/random_forest.py
qsar/models/ridge.py
qsar/models/xgboost.py
qsar/preprocessing/__init__.py
qsar/preprocessing/custom_preprocessing.py
qsar/preprocessing/feature_selector.py
qsar/utils/__init__.py
qsar/utils/cross_validator.py
qsar/utils/extractor.py
qsar/utils/hyperparameter_optimizer.py
qsar/utils/visualizer.py
tests/__init__.py
tests/test_cross_validator.py
tests/test_extract_descriptors.py
tests/test_feature_selector.py
tests/test_gan.py
tests/test_preprocessing.py
tests/test_qsar_gan_featurizer.py
qsarKit-0.0.1.dist-info/LICENSE
qsarKit-0.0.1.dist-info/METADATA
qsarKit-0.0.1.dist-info/WHEEL
qsarKit-0.0.1.dist-info/top_level.txt
qsarKit-0.0.1.dist-info/RECORD
