Metadata-Version: 2.1
Name: qsarKit
Version: 0.0.1
Summary: A Python package that offers robust predictive modeling using QSAR for evaluating the transfer of environmental contaminants in breast milk. It integrates multiple predictive models, provides synthetic data generation via GANs, and is tailored for researchers and health professionals.
Home-page: https://github.com/tahiri-lab/QSAR
Author: Tahiri Lab
Author-email: Tahiri Lab <nadia.tahiri@usherbrooke.ca>
Project-URL: Homepage, https://github.com/tahiri-lab/QSAR
Keywords: QSAR,Machine Learning,Chemoinformatics,Drug Discovery,Models,Metrics
Classifier: Programming Language :: Python :: 3
Classifier: License :: OSI Approved :: MIT License
Classifier: Operating System :: OS Independent
Requires-Python: ==3.10.*
License-File: LICENSE
Requires-Dist: catboost ~=1.2.2
Requires-Dist: deepchem ~=2.7.2.dev20231110055545
Requires-Dist: jax ~=0.4.20
Requires-Dist: keras ~=2.12.0
Requires-Dist: matplotlib ~=3.8.1
Requires-Dist: numpy ~=1.23.5
Requires-Dist: optuna ~=3.4.0
Requires-Dist: pandas ~=2.1.3
Requires-Dist: protobuf ~=4.25.1
Requires-Dist: rdkit ~=2023.9.1
Requires-Dist: scikit-learn ~=1.3.2
Requires-Dist: scipy ~=1.11.3
Requires-Dist: seaborn ~=0.13.0
Requires-Dist: statsmodels ~=0.14.0
Requires-Dist: torch ~=2.0.0
Requires-Dist: tqdm ~=4.66.1
Requires-Dist: xgboost ~=2.0.2
Requires-Dist: tensorflow ~=2.12.0
Requires-Dist: ipython ~=8.21.0
Requires-Dist: sphinx-rtd-theme ~=2.0.0
Requires-Dist: PyYAML ~=6.0.1
Provides-Extra: dev
Requires-Dist: flake8 ; extra == 'dev'
Requires-Dist: pytest ; extra == 'dev'
Requires-Dist: pytest-cov ; extra == 'dev'
Requires-Dist: pylint ; extra == 'dev'
Requires-Dist: black ; extra == 'dev'
Requires-Dist: isort ; extra == 'dev'
